litecow/__init__.py
litecow/client.py
litecow/common/__init__.py
litecow/common/common.py
litecow/common/litecow.proto
litecow/common/litecow_pb2.py
litecow/common/litecow_pb2_grpc.py
litecow/server.py
litecow-0.1.0.dist-info/entry_points.txt
litecow-0.1.0.dist-info/WHEEL
litecow-0.1.0.dist-info/METADATA
litecow-0.1.0.dist-info/RECORD
